gammafileops/__init__.py
gammafileops/archive.py
gammafileops/copy.py
gammafileops/delete.py
gammafileops/info.py
gammafileops/move.py
gammafileops/rename.py
gammafileops/utils/__init__.py
gammafileops-0.1.0.dist-info/licenses/LICENSE
gammafileops-0.1.0.dist-info/WHEEL
gammafileops-0.1.0.dist-info/METADATA
gammafileops-0.1.0.dist-info/RECORD
