Metadata-Version: 2.4
Name: gammafileops
Version: 0.1.0
Summary: gammafileops: A Python package for file operations including move, copy, delete, rename, archive, and info.
Home-page: https://www.husseingm73.github.io/projects/gammafileops
Author: HusseinGM
Author-email: husseingm73@gmail.com
License: MIT
License-File: LICENSE
